CHANGELOG.txt
LICENCE.txt
MANIFEST.in
README.txt
setup.py
hiramanijsn/__init__.py
hiramanijsn.egg-info/PKG-INFO
hiramanijsn.egg-info/SOURCES.txt
hiramanijsn.egg-info/dependency_links.txt
hiramanijsn.egg-info/top_level.txt