Metadata-Version: 2.1
Name: hiramanijsn
Version: 0.0.1
Summary: hiramanijsn
Home-page: 
Author: hiramanijsn
Author-email: hiramanijsn@gmail.com
License: MIT
Keywords: hiramanijsn
Classifier: Development Status :: 5 - Production/Stable
Classifier: Intended Audience :: Education
Classifier: Operating System :: Microsoft :: Windows :: Windows 10
Classifier: License :: OSI Approved :: MIT License
Classifier: Programming Language :: Python :: 3
License-File: LICENCE.txt
